{
  "openapi" : "3.0.1",
  "info" : {
    "title" : "defaultTitle",
    "description" : "defaultDescription",
    "version" : "0.1"
  },
  "servers" : [ {
    "url" : "http://localhost:3000"
  } ],
  "paths" : {
    "/api/v1/categories/:id" : {
      "put" : {
        "description" : "Modify category by id",
        "requestBody" : {
          "content" : {
            "application/json" : {
              "schema" : {
                "$ref" : "#/components/schemas/body"
              },
              "examples" : {
                "0" : {
                  "value" : "{\"name\": \"drinks\", \"description\":\"thirst-quenching beverage\"}"
                },
                "1" : {
                  "value" : "{\"name\": \"drinks\", \"description\":\"thirst-quenching beverage\"}"
                }
              }
            }
          }
        },
        "responses" : {
          "200" : {
            "description" : "OK",
            "content" : {
              "application/json; charset=utf-8" : {
                "schema" : {
                  "type" : "string"
                },
                "examples" : { }
              }
            }
          }
        },
        "servers" : [ {
          "url" : "http://localhost:3000"
        } ]
      },
      "delete" : {
        "description" : "Delete category by id",
        "responses" : {
          "200" : {
            "description" : "OK",
            "content" : {
              "application/json; charset=utf-8" : {
                "schema" : {
                  "type" : "string"
                },
                "examples" : { }
              }
            }
          }
        },
        "servers" : [ {
          "url" : "http://localhost:3000"
        } ]
      },
      "servers" : [ {
        "url" : "http://localhost:3000"
      } ]
    },
    "/api/v1/categories" : {
      "get" : {
        "description" : "Fetch all existing categories",
        "responses" : {
          "200" : {
            "description" : "OK",
            "content" : {
              "application/json; charset=utf-8" : {
                "schema" : {
                  "type" : "string"
                },
                "examples" : { }
              }
            }
          }
        },
        "servers" : [ {
          "url" : "http://localhost:3000"
        } ]
      },
      "post" : {
        "description" : "Post new category",
        "requestBody" : {
          "content" : {
            "application/json" : {
              "schema" : {
                "$ref" : "#/components/schemas/body_1"
              },
              "examples" : {
                "0" : {
                  "value" : "{\"name\": \"drinks\", \"description\":\"so thirsty\"}"
                }
              }
            }
          }
        },
        "responses" : {
          "200" : {
            "description" : "OK",
            "content" : {
              "application/json; charset=utf-8" : {
                "schema" : {
                  "type" : "string"
                },
                "examples" : { }
              }
            }
          }
        },
        "servers" : [ {
          "url" : "http://localhost:3000"
        } ]
      },
      "servers" : [ {
        "url" : "http://localhost:3000"
      } ]
    },
    "/api/v1/products/:id" : {
      "put" : {
        "description" : "Modify product by id",
        "requestBody" : {
          "content" : {
            "application/json" : {
              "schema" : {
                "$ref" : "#/components/schemas/body_2"
              },
              "examples" : {
                "0" : {
                  "value" : "{\"name\": \"drinks\", \"description\":\"thirst-quenching beverage\"}"
                },
                "1" : {
                  "value" : "{\"name\": \"drinks\", \"description\":\"thirst-quenching beverage\"}"
                }
              }
            }
          }
        },
        "responses" : {
          "200" : {
            "description" : "OK",
            "content" : {
              "application/json; charset=utf-8" : {
                "schema" : {
                  "type" : "string"
                },
                "examples" : { }
              }
            }
          }
        },
        "servers" : [ {
          "url" : "http://localhost:3000"
        } ]
      },
      "delete" : {
        "description" : "Delete product by id",
        "responses" : {
          "200" : {
            "description" : "OK",
            "content" : {
              "application/json; charset=utf-8" : {
                "schema" : {
                  "type" : "string"
                },
                "examples" : { }
              }
            }
          }
        },
        "servers" : [ {
          "url" : "http://localhost:3000"
        } ]
      },
      "servers" : [ {
        "url" : "http://localhost:3000"
      } ]
    },
    "/api/v1/products" : {
      "get" : {
        "description" : "Fetch all existing products",
        "responses" : {
          "200" : {
            "description" : "OK",
            "content" : {
              "application/json; charset=utf-8" : {
                "schema" : {
                  "type" : "string"
                },
                "examples" : { }
              }
            }
          }
        },
        "servers" : [ {
          "url" : "http://localhost:3000"
        } ]
      },
      "post" : {
        "description" : "Post new product",
        "requestBody" : {
          "content" : {
            "application/json" : {
              "schema" : {
                "$ref" : "#/components/schemas/body_3"
              },
              "examples" : {
                "0" : {
                  "value" : "{\"name\": \"drinks\", \"description\":\"so thirsty\"}"
                }
              }
            }
          }
        },
        "responses" : {
          "200" : {
            "description" : "OK",
            "content" : {
              "application/json; charset=utf-8" : {
                "schema" : {
                  "type" : "string"
                },
                "examples" : { }
              }
            }
          }
        },
        "servers" : [ {
          "url" : "http://localhost:3000"
        } ]
      },
      "servers" : [ {
        "url" : "http://localhost:3000"
      } ]
    }
  },
  "components" : {
    "schemas" : {
      "body" : {
        "type" : "object",
        "properties" : {
          "name" : {
            "type" : "string"
          },
          "description" : {
            "type" : "string"
          }
        }
      },
      "body_1" : {
        "type" : "object",
        "properties" : {
          "name" : {
            "type" : "string"
          },
          "description" : {
            "type" : "string"
          }
        }
      },
      "body_2" : {
        "type" : "object",
        "properties" : {
          "name" : {
            "type" : "string"
          },
          "description" : {
            "type" : "string"
          }
        }
      },
      "body_3" : {
        "type" : "object",
        "properties" : {
          "name" : {
            "type" : "string"
          },
          "description" : {
            "type" : "string"
          }
        }
      }
    }
  }
}